concurrency/__init__.py
concurrency/admin.py
concurrency/api.py
concurrency/apps.py
concurrency/compat.py
concurrency/config.py
concurrency/core.py
concurrency/exceptions.py
concurrency/fields.py
concurrency/forms.py
concurrency/middleware.py
concurrency/models.py
concurrency/triggers.py
concurrency/utils.py
concurrency/version.py
concurrency/views.py
concurrency/locale/en/LC_MESSAGES/django.po
concurrency/management/__init__.py
concurrency/management/commands/__init__.py
concurrency/management/commands/triggers.py
concurrency/templates/concurrency/delete_selected_confirmation.html
concurrency/templatetags/__init__.py
concurrency/templatetags/concurrency.py
django_concurrency-2.7.dist-info/METADATA
django_concurrency-2.7.dist-info/WHEEL
django_concurrency-2.7.dist-info/licenses/AUTHORS
django_concurrency-2.7.dist-info/licenses/LICENSE
django_concurrency-2.7.dist-info/RECORD
