Metadata-Version: 2.4
Name: django-concurrency
Version: 2.7
Summary: Optimistic lock implementation for Django. Prevents users from doing concurrent editing
Project-URL: downloads, https://github.com/saxix/django-concurrency
Project-URL: homepage, https://github.com/saxix/django-concurrency
Author-email: sax <s.apostolico@gmail.com>
License: MIT License
License-File: AUTHORS
License-File: LICENSE
Classifier: Environment :: Web Environment
Classifier: Framework :: Django
Classifier: Framework :: Django :: 3.2
Classifier: Framework :: Django :: 4.2
Classifier: Framework :: Django :: 5.1
Classifier: Intended Audience :: Developers
Classifier: Operating System :: OS Independent
Classifier: Programming Language :: Python :: 3 :: Only
Classifier: Programming Language :: Python :: 3.10
Classifier: Programming Language :: Python :: 3.11
Classifier: Programming Language :: Python :: 3.12
Classifier: Programming Language :: Python :: 3.13
Requires-Python: >=3.10
